pyfocalboard/__init__.py
pyfocalboard/api.py
pyfocalboard/types.py
pyfocalboard-1.0.2.dist-info/LICENSE.md
pyfocalboard-1.0.2.dist-info/METADATA
pyfocalboard-1.0.2.dist-info/WHEEL
pyfocalboard-1.0.2.dist-info/RECORD
