Metadata-Version: 2.1
Name: pyfocalboard
Version: 1.0.2
Summary: Python bindings for Focalboard HTTP API
License: MIT
Keywords: mattermost,focalboard
Author: Michal Karol
Author-email: michal.p.karol@gmail.com
Requires-Python: >=3.12,<4.0
Classifier: Development Status :: 4 - Beta
Classifier: Intended Audience :: Developers
Classifier: License :: OSI Approved :: MIT License
Classifier: Programming Language :: Python :: 3
Classifier: Programming Language :: Python :: 3.12
Classifier: Programming Language :: Python :: 3.13
Classifier: Programming Language :: Python :: 3.11
Classifier: Topic :: Communications :: Chat
Classifier: Topic :: Internet :: WWW/HTTP
Requires-Dist: dataclasses-json (>=0.6.7,<0.7.0)
Requires-Dist: requests (>=2.32.3,<3.0.0)
Requires-Dist: ruff (>=0.7.0,<0.8.0)
Project-URL: Changelog, https://github.com/MichalKarol/pyfocalboard/blob/main/CHANGELOG
Project-URL: Documentation, https://michalkarol.github.io/pyfocalboard/
Project-URL: Homepage, https://michalkarol.github.io/pyfocalboard/
Project-URL: Issues, https://github.com/MichalKarol/pyfocalboard/issues
Project-URL: Repository, https://github.com/MichalKarol/pyfocalboard
Project-URL: Releases, https://github.com/MichalKarol/pyfocalboard/releases
